cweb/__init__.py
cweb/cli.py
cweb/webapp.py
cweb/webservice.py
cWeb-1.0.0.dist-info/LICENSE.txt
cWeb-1.0.0.dist-info/METADATA
cWeb-1.0.0.dist-info/WHEEL
cWeb-1.0.0.dist-info/entry_points.txt
cWeb-1.0.0.dist-info/top_level.txt
cWeb-1.0.0.dist-info/RECORD
