Metadata-Version: 2.1
Name: cWeb
Version: 1.0.0
Summary: The client for web renders web pages and transforms them into whatever format you need.
Home-page: https://github.com/pyscaffold/pyscaffold/
Author: sanchezcarlosjr
Author-email: 24639141+sanchezcarlosjr@users.noreply.github.com
License: MIT
Project-URL: Documentation, https://pyscaffold.org/
Platform: any
Classifier: Development Status :: 4 - Beta
Classifier: Programming Language :: Python
License-File: LICENSE.txt
Requires-Dist: typer[all]
Requires-Dist: gradio
Requires-Dist: pydantic
Requires-Dist: playwright
Requires-Dist: fastapi
Requires-Dist: importlib-metadata ; python_version < "3.10"
Provides-Extra: testing
Requires-Dist: setuptools ; extra == 'testing'
Requires-Dist: pytest ; extra == 'testing'
Requires-Dist: pytest-cov ; extra == 'testing'
Provides-Extra: webapp
Requires-Dist: gradio ; extra == 'webapp'
Provides-Extra: webservice
Requires-Dist: fastapi ; extra == 'webservice'
